Metadata-Version: 2.1
Name: b4udata
Version: 0.1
Summary: Retrieve and edit data
Author-email: leonard@aps.holdings
License: UNKNOWN
Platform: UNKNOWN
